hi_esthercho_7/__init__.py
hi_esthercho_7-0.7.0.dist-info/METADATA
hi_esthercho_7-0.7.0.dist-info/WHEEL
hi_esthercho_7-0.7.0.dist-info/entry_points.txt
hi_esthercho_7-0.7.0.dist-info/top_level.txt
hi_esthercho_7-0.7.0.dist-info/RECORD
