Metadata-Version: 2.1
Name: hi_esthercho_7
Version: 0.7.0
Summary: Default template for PDM package
Author-email: EstherCho-7 <dkgkqm777@gmail.com>
License: MIT
Requires-Python: ==3.12.*
